chatora/app_config/__init__.py
chatora/app_config/_pkg_info.py
chatora/app_config/agg/__init__.py
chatora/app_config/agg/aggregator.py
chatora/app_config/agg/api.py
chatora/app_config/agg/constant.py
chatora.app_config-0.1.dist-info/LICENSE.txt
chatora.app_config-0.1.dist-info/METADATA
chatora.app_config-0.1.dist-info/WHEEL
chatora.app_config-0.1.dist-info/top_level.txt
chatora.app_config-0.1.dist-info/zip-safe
chatora.app_config-0.1.dist-info/RECORD
